gpit/__init__.py
gpit/cli_utilities.py
gpit/git_commands.py
gpit/main.py
gpit/openai_integration.py
gpit-0.0.4.dist-info/METADATA
gpit-0.0.4.dist-info/WHEEL
gpit-0.0.4.dist-info/entry_points.txt
gpit-0.0.4.dist-info/top_level.txt
gpit-0.0.4.dist-info/RECORD
