Metadata-Version: 2.1
Name: gpit
Version: 0.0.4
Summary: GPT-Powered Commit Assistance
Home-page: UNKNOWN
Author: Ofir Steinherz
Author-email: ofir.steinherz@gmail.com
License: UNKNOWN
Platform: UNKNOWN
Requires-Dist: requests
